napari_arnheim/__init__.py
napari_arnheim/access.cfg
napari_arnheim/context.py
napari_arnheim/dialogs/upload.py
napari_arnheim/forms/text_field.py
napari_arnheim/registries/napari.py
napari_arnheim/run.py
napari_arnheim/widgets/__init__.py
napari_arnheim/widgets/arnheim.py
napari_arnheim/widgets/base.py
napari_arnheim/widgets/context/__init__.py
napari_arnheim/widgets/context/arnheim_stage.py
napari_arnheim/widgets/context/context_aware.py
napari_arnheim/widgets/context/empty_stage.py
napari_arnheim/widgets/context/non_arnheim_stage.py
napari_arnheim/widgets/details/__init__.py
napari_arnheim/widgets/details/rep.py
napari_arnheim/widgets/dialogs/__init__.py
napari_arnheim/widgets/dialogs/forms/__init__.py
napari_arnheim/widgets/dialogs/forms/arnheim_model.py
napari_arnheim/widgets/dialogs/forms/base.py
napari_arnheim/widgets/dialogs/forms/fields/__init__.py
napari_arnheim/widgets/dialogs/forms/fields/base.py
napari_arnheim/widgets/dialogs/forms/fields/selectors/__init__.py
napari_arnheim/widgets/dialogs/forms/fields/selectors/arnheim_model.py
napari_arnheim/widgets/dialogs/forms/fields/selectors/base.py
napari_arnheim/widgets/dialogs/forms/fields/selectors/models/__init__.py
napari_arnheim/widgets/dialogs/forms/fields/selectors/models/experiment_selector.py
napari_arnheim/widgets/dialogs/forms/fields/selectors/models/sample_selector.py
napari_arnheim/widgets/dialogs/forms/fields/selectors/options_selector.py
napari_arnheim/widgets/dialogs/forms/fields/tags_field.py
napari_arnheim/widgets/dialogs/forms/fields/text_field.py
napari_arnheim/widgets/dialogs/forms/models/__init__.py
napari_arnheim/widgets/dialogs/forms/models/new_experiment.py
napari_arnheim/widgets/dialogs/forms/models/new_sample.py
napari_arnheim/widgets/dialogs/select_rep.py
napari_arnheim/widgets/dialogs/upload.py
napari_arnheim/widgets/error/error.py
napari_arnheim/widgets/helper.py
napari_arnheim/widgets/items/__init__.py
napari_arnheim/widgets/items/generatoritem.py
napari_arnheim-0.2.2.dist-info/entry_points.txt
napari_arnheim-0.2.2.dist-info/WHEEL
napari_arnheim-0.2.2.dist-info/METADATA
napari_arnheim-0.2.2.dist-info/RECORD
