Metadata-Version: 2.1
Name: napari-arnheim
Version: 0.2.2
Summary: Napari with Arnheim Client Integrated
Home-page: https://github.com/jhnnsrs/napari-arnheim
License: CC BY-NC 3.0
Author: jhnnsrs
Author-email: jhnnsrs@gmail.com
Requires-Python: >=3.7,<3.10
Classifier: License :: Other/Proprietary License
Classifier: Programming Language :: Python :: 3
Classifier: Programming Language :: Python :: 3.7
Classifier: Programming Language :: Python :: 3.8
Classifier: Programming Language :: Python :: 3.9
Requires-Dist: PyQt5 (>=5.15.4,<6.0.0)
Requires-Dist: PyQtWebEngine (>=5.15.4,<6.0.0)
Requires-Dist: grunnlag (>=0.4.20,<0.5.0)
Requires-Dist: napari (>=0.4.8,<0.5.0)
Requires-Dist: qasync (>=0.13.0,<0.14.0)
